NGAsubGMM.py
NGAsubGMM-0.0.3.dist-info/METADATA
NGAsubGMM-0.0.3.dist-info/WHEEL
NGAsubGMM-0.0.3.dist-info/top_level.txt
NGAsubGMM-0.0.3.dist-info/RECORD
